LICENSE
MANIFEST.in
Makefile
README.md
requirements.txt
setup.py
zmqmin/__init__.py
zmqmin/client.py
zmqmin/devices.py
zmqmin/log.py
zmqmin/messenger.py
zmqmin/process.py
zmqmin/publisher.py
zmqmin/receiver.py
zmqmin/sender.py
zmqmin/server.py
zmqmin/subscriber.py
zmqmin.egg-info/PKG-INFO
zmqmin.egg-info/SOURCES.txt
zmqmin.egg-info/dependency_links.txt
zmqmin.egg-info/requires.txt
zmqmin.egg-info/top_level.txt