Metadata-Version: 1.1
Name: zmqmin
Version: 14.1.1.0.1
Summary: Simplified python interface for ZMQ.
Home-page: http://www.github.com/jtimon/zmqmin/
Author: Jorge Timon
Author-email: jtimon@monetize.io
License: UNKNOWN
Download-URL: http://pypi.python.org/packages/source/p/zmqmin/zmqmin-14.1.1.0.1.tar.gz
Platform: UNKNOWN
Classifier: Development Status :: 3 - Alpha
Classifier: Intended Audience :: Developers
Classifier: License :: OSI Approved :: MIT License
Classifier: Operating System :: OS Independent
Classifier: Programming Language :: Python
Classifier: Topic :: Software Development :: Libraries :: Python Modules
